assign_reviewers/__init__.py
assign_reviewers/assign_reviewers.py
assign_reviewers-0.2.3.dist-info/LICENSE
assign_reviewers-0.2.3.dist-info/METADATA
assign_reviewers-0.2.3.dist-info/WHEEL
assign_reviewers-0.2.3.dist-info/entry_points.txt
assign_reviewers-0.2.3.dist-info/top_level.txt
assign_reviewers-0.2.3.dist-info/RECORD
