Metadata-Version: 2.1
Name: assign-reviewers
Version: 0.2.3
Summary: Assign reviewers and create scoring excel sheets.
Home-page: https://github.com/jcohenadad/assign-reviewers
Author: Julien Cohen-Adad
Author-email: jcohen@polymtl.ca
License: LICENSE
Platform: UNKNOWN
Requires-Dist: pandas
Requires-Dist: pytest
Requires-Dist: pytest-cov
